README.md
setup.py
manimnx/__init__.py
manimnx/manimnx.py
manimnx.egg-info/PKG-INFO
manimnx.egg-info/SOURCES.txt
manimnx.egg-info/dependency_links.txt
manimnx.egg-info/not-zip-safe
manimnx.egg-info/requires.txt
manimnx.egg-info/top_level.txt