Metadata-Version: 1.0
Name: manimnx
Version: 0.1.1
Summary: Interface between `manim` and `networkx`
Home-page: https://github.com/rajatvd/manim-nx
Author: Rajat Vadiraj Dwaraknath
Author-email: rajatvd@gmail.com
License: MIT
Platform: UNKNOWN
